keyed_classes/__init__.py
keyed_classes-0.1.0.dist-info/WHEEL
keyed_classes-0.1.0.dist-info/METADATA
keyed_classes-0.1.0.dist-info/RECORD
