Metadata-Version: 2.1
Name: keyed-classes
Version: 0.1.0
Summary: Create pseudo-singleton key based objects like those generated by logging.getLogger
Home-page: https://github.com/buckley-w-david/keyed-classes/
License: MIT
Author: David Buckley
Author-email: buckley.w.david@gmail.com
Classifier: License :: OSI Approved :: MIT License
Classifier: Programming Language :: Python :: 2
Classifier: Programming Language :: Python :: 2.7
Classifier: Programming Language :: Python :: 3
Classifier: Programming Language :: Python :: 3.4
Classifier: Programming Language :: Python :: 3.5
Classifier: Programming Language :: Python :: 3.6
Classifier: Programming Language :: Python :: 3.7
